dj_pony/__init__.py
dj_pony/hashedfield/__init__.py
dj_pony/hashedfield/apps.py
dj_pony/hashedfield/fields.py
dj_pony/hashedfield/managers.py
dj_pony/hashedfield/managers_base.py
dj_pony/hashedfield/models_base.py
dj_pony.hashedfield-0.4.0.dist-info/LICENSE
dj_pony.hashedfield-0.4.0.dist-info/WHEEL
dj_pony.hashedfield-0.4.0.dist-info/METADATA
dj_pony.hashedfield-0.4.0.dist-info/RECORD
