Metadata-Version: 2.1
Name: dj-pony.hashedfield
Version: 0.4.0
Summary: A Hashed Field for Django that does all the work for you.
Author: Samuel Bishop
Author-email: sam@techdragon.io
Requires-Python: >=3.6,<4.0
Classifier: Programming Language :: Python :: 3
Classifier: Programming Language :: Python :: 3.6
Classifier: Programming Language :: Python :: 3.7
Requires-Dist: django (>=2.2)
Requires-Dist: sentinel (>=0.1.2,<0.2.0)
